README.md
setup.py
peregrinearb/__init__.py
peregrinearb/async_build_markets.py
peregrinearb/async_find_opportunities.py
peregrinearb/bellman_multi_graph.py
peregrinearb/bellmannx.py
peregrinearb/outliers.py
peregrinearb.egg-info/PKG-INFO
peregrinearb.egg-info/SOURCES.txt
peregrinearb.egg-info/dependency_links.txt
peregrinearb.egg-info/top_level.txt
peregrinearb/tests/__init__.py
peregrinearb/tests/bellmannx_test.py
peregrinearb/tests/test_build_markets.py
peregrinearb/tests/test_misc.py
peregrinearb/tests/utils_test.py
peregrinearb/utils/__init__.py
peregrinearb/utils/data_structures.py
peregrinearb/utils/drawing.py
peregrinearb/utils/general.py
peregrinearb/utils/graph_utils.py
peregrinearb/utils/misc.py
peregrinearb/utils/multi_exchange.py
peregrinearb/utils/single_exchange.py