Metadata-Version: 1.0
Name: peregrinearb
Version: 1.0.2
Summary: A Python library which provides several algorithms to detect arbitrage opportunities across over 90 cryptocurrency markets in 34 countries
Home-page: https://github.com/wardbradt/peregrinearb
Author: Ward Bradt
Author-email: wardbradt5@gmail.com
License: MIT
Platform: UNKNOWN
